salstools/__init__.py
salstools/main.py
salstools/py.typed.py
salstools-0.1.4.6.dist-info/METADATA
salstools-0.1.4.6.dist-info/WHEEL
salstools-0.1.4.6.dist-info/top_level.txt
salstools-0.1.4.6.dist-info/RECORD
