Metadata-Version: 2.4
Name: salstools
Version: 0.1.4.6
Summary: Utilities for charts and analytics
Author: Sals
Classifier: Programming Language :: Python :: 3
Classifier: License :: OSI Approved :: MIT License
Requires-Python: >=3.9
Requires-Dist: pandas
Requires-Dist: numpy
Requires-Dist: matplotlib
